eisp/__init__.py
eisp/ensemble.py
eisp/proxy_tasks.py
eisp/visualization.py
eisp-0.3.8.dist-info/licenses/LICENSE
eisp-0.3.8.dist-info/WHEEL
eisp-0.3.8.dist-info/METADATA
eisp-0.3.8.dist-info/RECORD
