Metadata-Version: 2.4
Name: eisp
Version: 0.3.8
Summary: A framework using an ensemble for inference on sensitive data using proxy tasks.
Author: Clara Ernesto
Author-email: Clara Ernesto <clrcera05@gmail.com>
License-Expression: MIT
License-File: LICENSE
Classifier: Programming Language :: Python :: 3
Classifier: Operating System :: OS Independent
Requires-Dist: joblib>=1.5.2
Requires-Dist: matplotlib>=3.10.7
Requires-Dist: numpy>=1.26.4
Requires-Dist: optuna>=4.5.0
Requires-Dist: scikit-learn>=1.7.2
Requires-Dist: shap>=0.49.1
Requires-Dist: torch>=2.8.0
Requires-Dist: torchvision>=0.23.0
Requires-Dist: tqdm>=4.67.1
Requires-Dist: typing-extensions>=4.15.0
Requires-Dist: umap-learn>=0.5.9.post2
Requires-Dist: xgboost>=3.0.5
Requires-Python: >=3.10
Project-URL: Homepage, https://github.com/araceli-project/eisp
Project-URL: Issues, https://github.com/araceli-project/eisp/issues
